gradio_rag_sources/__init__.py
gradio_rag_sources/ragsources.py
gradio_rag_sources-0.1.3.dist-info/METADATA
gradio_rag_sources-0.1.3.dist-info/WHEEL
gradio_rag_sources-0.1.3.dist-info/RECORD
